quotly/Quote.py
quotly/Quotly.py
quotly/QuotyBot.py
quotly/__init__.py
quotly/__main__.py
web/__init__.py
web/app.py
quotly-0.2.3.dist-info/METADATA
quotly-0.2.3.dist-info/WHEEL
quotly-0.2.3.dist-info/top_level.txt
quotly-0.2.3.dist-info/RECORD
