Metadata-Version: 2.1
Name: quotly
Version: 0.2.3
Summary: A quoting bot for the "Discord Hack Week"
Home-page: https://github.com/Schrotty/quotly
Author: Schrotty
Author-email: rubenmaurer@live.de
License: MIT
Keywords: discord discord-bot
Platform: UNKNOWN
Classifier: Programming Language :: Python :: 3.7
Classifier: License :: OSI Approved :: MIT License
Classifier: Operating System :: OS Independent
Requires-Dist: python-dotenv
Requires-Dist: discord.py
